LICENSE
MANIFEST.in
README.md
flake8_doubles.py
setup.py
flake8_doubles.egg-info/PKG-INFO
flake8_doubles.egg-info/SOURCES.txt
flake8_doubles.egg-info/dependency_links.txt
flake8_doubles.egg-info/entry_points.txt
flake8_doubles.egg-info/not-zip-safe
flake8_doubles.egg-info/top_level.txt