Metadata-Version: 1.1
Name: flake8-doubles
Version: 0.3
Summary: flake8 doubles checker, ensures mock.patch is not used
Home-page: https://github.com/jiazou/flake8-doubles
Author: Jia Zou
Author-email: jiazou@uber.com
License: Expat license
Keywords: flake8 doubles
Platform: UNKNOWN
Classifier: Development Status :: 3 - Alpha
Classifier: Environment :: Console
Classifier: Intended Audience :: Developers
Classifier: License :: OSI Approved :: MIT License
Classifier: Operating System :: OS Independent
Classifier: Programming Language :: Python
Classifier: Programming Language :: Python :: 2
Classifier: Programming Language :: Python :: 3
Classifier: Topic :: Software Development :: Libraries :: Python Modules
Classifier: Topic :: Software Development :: Quality Assurance
